{
  "db": {
    "name": "db",
    "connector": "memory"
  },
  "postgres_local": {
    "host": "localhost",
    "port": 5432,
    "database": "fftoolbox",
    "password": "Zuela32!",
    "name": "postgres",
    "user": "dubcdr",
    "schema": "fftoolbox",
    "connector": "postgresql"
  },
  "postgres": {
    "host": "fftoolbox.cc7r5nw8kinb.us-west-2.rds.amazonaws.com",
    "port": 5432,
    "database": "fftoolbox",
    "password": "Zuela32!",
    "name": "postgres",
    "user": "dubcdr",
    "schema": "fftoolbox",
    "connector": "postgresql"
  }
}
